synapse_counting/__init__.py
synapse_counting/calc_synaptic_coloc.py
synapse_counting/calc_synaptic_metrics.py
synapse_counting/helpers.py
synapse_counting/metadata.py
synapse_counting/preprocessing.py
synapse_counting/results_plotting.py
synapse_counting-0.0.2.dist-info/LICENSE
synapse_counting-0.0.2.dist-info/METADATA
synapse_counting-0.0.2.dist-info/WHEEL
synapse_counting-0.0.2.dist-info/top_level.txt
synapse_counting-0.0.2.dist-info/RECORD
